high_lvl_networking/__init__.py
high_lvl_networking/networking.py
high_lvl_networking-0.1.0.dist-info/METADATA
high_lvl_networking-0.1.0.dist-info/WHEEL
high_lvl_networking-0.1.0.dist-info/top_level.txt
high_lvl_networking-0.1.0.dist-info/RECORD
