Metadata-Version: 2.1
Name: high-lvl-networking
Version: 0.1.0
Summary: High level library to setup networking
Home-page: UNKNOWN
Author: Silvan Schmidt
License: MIT
Platform: UNKNOWN
